<?xml version="1.0" encoding="utf-8"?>
<!DOCTYPE hibernate-mapping PUBLIC "-//Hibernate/Hibernate Mapping DTD 3.0//EN"
"http://www.hibernate.org/dtd/hibernate-mapping-3.0.dtd">
<!-- 
    Mapping file autogenerated by MyEclipse Persistence Tools
-->
<hibernate-mapping>
    <class name="pers.sg.kms.model.Goschoolstate" table="goschoolstate" catalog="kms">
        <id name="goSchoolStateId" type="short">
            <column name="GoSchoolStateID" />
            <generator class="identity" />
        </id>
        <property name="goSchoolStateName" type="string">
            <column name="GoSchoolStateName" length="25" />
        </property>
        <set name="goschoolrecords" inverse="true">
            <key>
                <column name="GoSchoolStateID" />
            </key>
            <one-to-many class="pers.sg.kms.model.Goschoolrecord" />
        </set>
    </class>
</hibernate-mapping>
